neurolucidaxml2ex.py
neurolucidaxml2ex-0.1.2.dist-info/METADATA
neurolucidaxml2ex-0.1.2.dist-info/RECORD
neurolucidaxml2ex-0.1.2.dist-info/WHEEL
neurolucidaxml2ex-0.1.2.dist-info/entry_points.txt
neurolucidaxml2ex-0.1.2.dist-info/top_level.txt
