Metadata-Version: 2.1
Name: neurolucidaxml2ex
Version: 0.1.2
Summary: Python client for generating Ex format model descriptions from Neurolucida XML.
Home-page: https://github.com/hsorby/neurolucidaxml2ex
Author: Auckland Bioengineering Institute
Author-email: h.sorby@auckland.ac.nz
License: Apache Software License
Requires-Dist: opencmiss.zinc
